odoo/addons/web_widget_domain_editor_dialog/README.rst
odoo/addons/web_widget_domain_editor_dialog/__init__.py
odoo/addons/web_widget_domain_editor_dialog/__manifest__.py
odoo/addons/web_widget_domain_editor_dialog/i18n/es.po
odoo/addons/web_widget_domain_editor_dialog/i18n/it.po
odoo/addons/web_widget_domain_editor_dialog/i18n/web_widget_domain_editor_dialog.pot
odoo/addons/web_widget_domain_editor_dialog/i18n/zh_CN.po
odoo/addons/web_widget_domain_editor_dialog/readme/CONTRIBUTORS.md
odoo/addons/web_widget_domain_editor_dialog/readme/DESCRIPTION.md
odoo/addons/web_widget_domain_editor_dialog/readme/USAGE.md
odoo/addons/web_widget_domain_editor_dialog/static/description/icon.png
odoo/addons/web_widget_domain_editor_dialog/static/description/index.html
odoo/addons/web_widget_domain_editor_dialog/static/src/img/behaviour.gif
odoo/addons/web_widget_domain_editor_dialog/static/src/js/domain_field.esm.js
odoo/addons/web_widget_domain_editor_dialog/static/src/js/widget_domain_editor_dialog.esm.js
odoo_addon_web_widget_domain_editor_dialog-18.0.1.0.0.2.dist-info/METADATA
odoo_addon_web_widget_domain_editor_dialog-18.0.1.0.0.2.dist-info/WHEEL
odoo_addon_web_widget_domain_editor_dialog-18.0.1.0.0.2.dist-info/top_level.txt
odoo_addon_web_widget_domain_editor_dialog-18.0.1.0.0.2.dist-info/RECORD
